doobots/__init__.py
doobots/base_message.py
doobots/file.py
doobots/local_runner.py
doobots/packager.py
doobots/request.py
doobots/response.py
doobots/utils.py
doobots-1.0.5.dist-info/METADATA
doobots-1.0.5.dist-info/WHEEL
doobots-1.0.5.dist-info/entry_points.txt
doobots-1.0.5.dist-info/top_level.txt
doobots-1.0.5.dist-info/RECORD
