Metadata-Version: 2.4
Name: doobots
Version: 1.0.5
Summary: Helpers do DooBots para execução de código do usuário
Author: Dootax
License: MIT
Project-URL: Homepage, https://github.com/Dootax/doobots-python
Project-URL: Source, https://github.com/Dootax/doobots-python
Keywords: doobots,dootax
Classifier: License :: OSI Approved :: MIT License
Classifier: Programming Language :: Python :: 3
Classifier: Programming Language :: Python :: 3 :: Only
Classifier: Programming Language :: Python :: 3.8
Classifier: Programming Language :: Python :: 3.9
Classifier: Programming Language :: Python :: 3.10
Requires-Python: >=3.8
Requires-Dist: toml>=0.10.2
